umerfy_number/__init__.py
umerfy_number/test.py
umerfy_number-0.1.dist-info/LICENSE.txt
umerfy_number-0.1.dist-info/METADATA
umerfy_number-0.1.dist-info/WHEEL
umerfy_number-0.1.dist-info/top_level.txt
umerfy_number-0.1.dist-info/RECORD
