Metadata-Version: 2.1
Name: umerfy_number
Version: 0.1
Summary: To convert numbers to human readable format
Author: Muhmmad Umer
Author-email: umernadeem241@gmail.com
License-File: LICENSE.txt
